phoenix_tracer/__init__.py
phoenix_tracer/py.typed
phoenix_tracer/tracer.py
promptimus_phoenix_tracer-0.1.4.dist-info/METADATA
promptimus_phoenix_tracer-0.1.4.dist-info/WHEEL
promptimus_phoenix_tracer-0.1.4.dist-info/RECORD
