Metadata-Version: 2.4
Name: promptimus-phoenix-tracer
Version: 0.1.4
Summary: A plugin with arize-phoenix tracing for promptimus.
Author-email: ailadin <korzhukandrew@gmail.com>
Requires-Python: >=3.12
Requires-Dist: arize-phoenix-otel>=0.8.0
Requires-Dist: arize-phoenix>=8.20.0
Requires-Dist: openinference-semantic-conventions>=0.1.14
